ma_python_package/__init__.py
ma_python_package/data_check.py
ma_python_package/data_processing.py
ma_python_package/data_summary.py
ma_python_package/data_utils.py
ma_python_package/data_visualization.py
ma_python_package/workflow_management.py
ma_python_package-0.0.36.dist-info/METADATA
ma_python_package-0.0.36.dist-info/WHEEL
ma_python_package-0.0.36.dist-info/RECORD
