Metadata-Version: 2.4
Name: ma_python_package
Version: 0.0.36
Summary: Streamline data preprocessing and enhance analysis with our Powerful Data Preparation Package.
Author-email: MASS Analytics <info@mass-analytics.com>
Classifier: Development Status :: 2 - Pre-Alpha
Classifier: Environment :: Console
Classifier: Intended Audience :: Science/Research
Classifier: License :: OSI Approved :: Apache Software License
Classifier: Natural Language :: English
Classifier: Operating System :: OS Independent
Classifier: Programming Language :: Python
Classifier: Programming Language :: Python :: 3
Classifier: Programming Language :: Python :: 3 :: Only
Classifier: Programming Language :: Python :: 3.7
Classifier: Programming Language :: Python :: 3.8
Classifier: Programming Language :: Python :: 3.9
Classifier: Programming Language :: Python :: 3.10
Classifier: Programming Language :: Python :: 3.11
Requires-Python: >=3.9
Requires-Dist: odfpy==1.4.1
Requires-Dist: openpyxl==3.1.2
Requires-Dist: plotly==5.19.0
Requires-Dist: pyspark==3.5.1
Requires-Dist: pyxlsb==1.0.10
Requires-Dist: streamlit-option-menu==0.3.13
Requires-Dist: streamlit==1.32.1
Requires-Dist: tqdm
Requires-Dist: xlsxwriter==3.2.0
